PyBMF/__init__.py
PyBMF/datasets/BaseData.py
PyBMF/datasets/BaseSplit.py
PyBMF/datasets/CrossValidation.py
PyBMF/datasets/MovieLensData.py
PyBMF/datasets/MovieLensGenreCastData.py
PyBMF/datasets/MovieLensGenreCastUserData.py
PyBMF/datasets/MovieLensUserData.py
PyBMF/datasets/NetflixData.py
PyBMF/datasets/NetflixGenreCastData.py
PyBMF/datasets/NoSplit.py
PyBMF/datasets/RatioSplit.py
PyBMF/datasets/__init__.py
PyBMF/generators/BaseGenerator.py
PyBMF/generators/BlockDiagonalMatrixGenerator.py
PyBMF/generators/BlockMatrixGenerator.py
PyBMF/generators/SyntheticMatrixGenerator.py
PyBMF/generators/__init__.py
PyBMF/models/Asso.py
PyBMF/models/AssoExAlternateMultipleWeights.py
PyBMF/models/AssoIter.py
PyBMF/models/AssoOpt.py
PyBMF/models/BMFAlternate.py
PyBMF/models/BMFCollective.py
PyBMF/models/BMFInterleave.py
PyBMF/models/BMFTools.py
PyBMF/models/BaseCollectiveModel.py
PyBMF/models/BaseModel.py
PyBMF/models/BaseModelTools.py
PyBMF/models/BinaryMFPenalty.py
PyBMF/models/BinaryMFPenaltyExCollective.py
PyBMF/models/BinaryMFThreshold.py
PyBMF/models/BinaryMFThresholdExCollective.py
PyBMF/models/BinaryMFThresholdExColumnwise.py
PyBMF/models/BinaryMFThresholdExSigmoid.py
PyBMF/models/BinaryMFThresholdExSigmoidColumnwise.py
PyBMF/models/BinaryMFThresholdExSigmoidColumnwiseLamda.py
PyBMF/models/CMF.py
PyBMF/models/ContinuousCollectiveModel.py
PyBMF/models/ContinuousModel.py
PyBMF/models/ELBMF.py
PyBMF/models/ELBMFNumPy.py
PyBMF/models/ELBMFPyTorch.py
PyBMF/models/FastStep.py
PyBMF/models/GreConD.py
PyBMF/models/GreConDPlus.py
PyBMF/models/Hyper.py
PyBMF/models/HyperPlus.py
PyBMF/models/IP.py
PyBMF/models/MEBF.py
PyBMF/models/MaxSAT.py
PyBMF/models/MessagePassing.py
PyBMF/models/NMFSklearn.py
PyBMF/models/OrMachine.py
PyBMF/models/PNLPF.py
PyBMF/models/PRIMP.py
PyBMF/models/PRIMPPyTorch.py
PyBMF/models/Panda.py
PyBMF/models/RSNMF.py
PyBMF/models/TransposedModel.py
PyBMF/models/WNMF.py
PyBMF/models/__init__.py
PyBMF/solvers/__init__.py
PyBMF/solvers/line_search.py
PyBMF-0.0.1.dist-info/LICENSE
PyBMF-0.0.1.dist-info/METADATA
PyBMF-0.0.1.dist-info/WHEEL
PyBMF-0.0.1.dist-info/top_level.txt
PyBMF-0.0.1.dist-info/RECORD
