Metadata-Version: 2.1
Name: PyBMF
Version: 0.0.1
Summary: A Python library for Boolean Matrix Factorization
Home-page: https://github.com/felixnie/PyBMF
Author: Hongtuo Nie
Author-email: Hongtuo Nie <nie.ht@outlook.com>
Maintainer-email: Hongtuo Nie <nie.ht@outlook.com>
License: Copyright (c) 2024 The PyBMF Authors
Project-URL: Homepage, https://github.com/PreferredAI/PyBMF
Project-URL: Issues, https://github.com/PreferredAI/PyBMF/issues
Keywords: Boolean,binary,matrix,factorization,decomposition,testbench
Classifier: Development Status :: 4 - Beta
Classifier: Programming Language :: Python :: 3
Classifier: License :: OSI Approved :: MIT License
Classifier: Operating System :: OS Independent
Requires-Python: >=3.9
License-File: LICENSE
Requires-Dist: Cython
Requires-Dist: ipython
Requires-Dist: matplotlib
Requires-Dist: mlxtend
Requires-Dist: networkx
Requires-Dist: numpy
Requires-Dist: p-tqdm
Requires-Dist: pandas
Requires-Dist: scikit-learn
Requires-Dist: scipy
Requires-Dist: setuptools
Requires-Dist: tqdm
Requires-Dist: uszipcode
